{
    "_width": 8,
    "_height": 8,
    "_heightBytes": 1,
    "_proportionalFont": true,
    "_spacing": 2,
    "_replacementChar": "_",
    "_widthLookup": [
        2,
        1,
        3,
        5,
        5,
        7,
        5,
        1,
        3,
        3,
        5,
        5,
        2,
        3,
        1,
        4,
        5,
        5,
        5,
        5,
        5,
        5,
        5,
        5,
        5,
        5,
        1,
        1,
        4,
        5,
        4,
        4,
        7,
        5,
        5,
        5,
        5,
        5,
        5,
        5,
        5,
        3,
        4,
        5,
        5,
        5,
        5,
        5,
        5,
        5,
        5,
        5,
        5,
        5,
        5,
        5,
        5,
        5,
        5,
        3,
        4,
        3,
        5,
        5,
        2,
        5,
        5,
        4,
        5,
        5,
        4,
        5,
        4,
        1,
        2,
        4,
        2,
        5,
        4,
        4,
        5,
        5,
        4,
        4,
        4,
        4,
        5,
        7,
        5,
        4,
        4,
        4,
        2,
        4,
        5,
        4,
        5,
        2,
        4,
        8,
        3,
        3,
        4,
        9,
        3,
        6,
        2,
        2,
        4,
        4,
        4,
        4,
        4,
        6,
        3,
        5,
        4,
        4,
        5,
        5,
        2,
        4,
        5,
        6,
        3,
        5,
        4,
        3,
        7,
        5,
        4,
        5,
        3,
        3,
        2,
        4,
        5,
        2,
        3,
        2,
        4,
        5,
        6,
        6,
        6,
        4,
        5,
        5,
        5,
        5,
        5,
        5,
        5,
        4,
        4,
        4,
        4,
        4,
        3,
        3,
        3,
        3,
        5,
        5,
        5,
        5,
        5,
        5,
        5,
        5,
        5,
        4,
        4,
        4,
        4,
        5,
        4,
        4,
        4,
        4,
        4,
        4,
        4,
        4,
        5,
        3,
        4,
        4,
        4,
        4,
        2,
        2,
        3,
        3,
        4,
        4,
        4,
        4,
        4,
        4,
        4,
        5,
        4,
        4,
        4,
        4,
        4,
        3,
        3,
        3
    ],
    "_positionLookup": [
        0,
        2,
        3,
        6,
        11,
        16,
        23,
        28,
        29,
        32,
        35,
        40,
        45,
        47,
        50,
        51,
        55,
        60,
        65,
        70,
        75,
        80,
        85,
        90,
        95,
        100,
        105,
        106,
        107,
        111,
        116,
        120,
        124,
        131,
        136,
        141,
        146,
        151,
        156,
        161,
        166,
        171,
        174,
        178,
        183,
        188,
        193,
        198,
        203,
        208,
        213,
        218,
        223,
        228,
        233,
        238,
        243,
        248,
        253,
        258,
        261,
        265,
        268,
        273,
        278,
        280,
        285,
        290,
        294,
        299,
        304,
        308,
        313,
        317,
        318,
        320,
        324,
        326,
        331,
        335,
        339,
        344,
        349,
        353,
        357,
        361,
        365,
        370,
        377,
        382,
        386,
        390,
        394,
        396,
        400,
        405,
        409,
        414,
        416,
        420,
        428,
        431,
        434,
        438,
        447,
        450,
        456,
        458,
        460,
        464,
        468,
        472,
        476,
        480,
        486,
        489,
        494,
        498,
        502,
        507,
        512,
        514,
        518,
        523,
        529,
        532,
        537,
        541,
        544,
        551,
        556,
        560,
        565,
        568,
        571,
        573,
        577,
        582,
        584,
        587,
        589,
        593,
        598,
        604,
        610,
        616,
        620,
        625,
        630,
        635,
        640,
        645,
        650,
        655,
        659,
        663,
        667,
        671,
        675,
        678,
        681,
        684,
        687,
        692,
        697,
        702,
        707,
        712,
        717,
        722,
        727,
        732,
        736,
        740,
        744,
        748,
        753,
        757,
        761,
        765,
        769,
        773,
        777,
        781,
        785,
        790,
        793,
        797,
        801,
        805,
        809,
        811,
        813,
        816,
        819,
        823,
        827,
        831,
        835,
        839,
        843,
        847,
        852,
        856,
        860,
        864,
        868,
        872,
        875,
        878
    ],
    "_bitmap": {
        "type": "Buffer",
        "data": [
            0,
            0,
            95,
            7,
            0,
            7,
            116,
            28,
            119,
            28,
            23,
            46,
            106,
            62,
            43,
            58,
            6,
            73,
            54,
            8,
            54,
            73,
            48,
            54,
            73,
            89,
            118,
            72,
            7,
            60,
            66,
            129,
            129,
            66,
            60,
            10,
            4,
            31,
            4,
            10,
            8,
            8,
            62,
            8,
            8,
            128,
            96,
            8,
            8,
            8,
            64,
            192,
            48,
            12,
            3,
            62,
            65,
            65,
            65,
            62,
            68,
            66,
            127,
            64,
            64,
            70,
            97,
            81,
            73,
            70,
            34,
            65,
            73,
            73,
            54,
            24,
            20,
            18,
            127,
            16,
            39,
            69,
            69,
            69,
            57,
            62,
            73,
            73,
            73,
            48,
            1,
            1,
            113,
            13,
            3,
            54,
            73,
            73,
            73,
            54,
            6,
            73,
            73,
            41,
            30,
            54,
            208,
            8,
            20,
            34,
            65,
            20,
            20,
            20,
            20,
            20,
            65,
            34,
            20,
            8,
            2,
            81,
            9,
            6,
            60,
            66,
            153,
            165,
            189,
            66,
            28,
            124,
            18,
            17,
            18,
            124,
            127,
            73,
            73,
            73,
            54,
            62,
            65,
            65,
            65,
            34,
            127,
            65,
            65,
            65,
            62,
            127,
            73,
            73,
            73,
            65,
            127,
            9,
            9,
            9,
            1,
            62,
            65,
            73,
            73,
            122,
            127,
            8,
            8,
            8,
            127,
            65,
            127,
            65,
            64,
            65,
            65,
            63,
            127,
            8,
            20,
            34,
            65,
            127,
            64,
            64,
            64,
            64,
            127,
            6,
            12,
            6,
            127,
            127,
            6,
            8,
            48,
            127,
            62,
            65,
            65,
            65,
            62,
            127,
            9,
            9,
            9,
            6,
            62,
            65,
            97,
            193,
            190,
            127,
            9,
            25,
            41,
            70,
            38,
            73,
            73,
            73,
            50,
            1,
            1,
            127,
            1,
            1,
            63,
            64,
            64,
            64,
            63,
            7,
            56,
            64,
            56,
            7,
            31,
            96,
            31,
            96,
            31,
            99,
            20,
            8,
            20,
            99,
            1,
            6,
            120,
            6,
            1,
            97,
            81,
            73,
            69,
            67,
            127,
            65,
            65,
            3,
            12,
            48,
            192,
            65,
            65,
            127,
            4,
            2,
            1,
            2,
            4,
            128,
            128,
            128,
            128,
            128,
            1,
            2,
            32,
            84,
            84,
            84,
            120,
            127,
            68,
            68,
            68,
            56,
            56,
            68,
            68,
            68,
            56,
            68,
            68,
            68,
            127,
            56,
            84,
            84,
            84,
            88,
            8,
            126,
            9,
            1,
            24,
            164,
            164,
            164,
            120,
            127,
            4,
            4,
            120,
            125,
            128,
            125,
            127,
            16,
            40,
            68,
            63,
            64,
            124,
            4,
            120,
            4,
            120,
            124,
            4,
            4,
            120,
            56,
            68,
            68,
            56,
            252,
            36,
            36,
            36,
            24,
            24,
            36,
            36,
            36,
            252,
            124,
            8,
            4,
            4,
            72,
            84,
            84,
            36,
            4,
            63,
            68,
            64,
            60,
            64,
            64,
            124,
            28,
            32,
            64,
            32,
            28,
            28,
            96,
            96,
            28,
            96,
            96,
            28,
            68,
            40,
            16,
            40,
            68,
            156,
            160,
            96,
            28,
            100,
            84,
            84,
            76,
            24,
            126,
            129,
            129,
            255,
            255,
            129,
            129,
            126,
            24,
            24,
            4,
            8,
            16,
            12,
            20,
            62,
            85,
            85,
            255,
            129,
            129,
            129,
            255,
            128,
            96,
            128,
            96,
            128,
            96,
            96,
            96,
            0,
            96,
            96,
            0,
            96,
            96,
            4,
            127,
            4,
            20,
            127,
            20,
            2,
            1,
            1,
            2,
            70,
            41,
            22,
            8,
            52,
            74,
            49,
            72,
            48,
            0,
            24,
            36,
            62,
            65,
            34,
            127,
            73,
            65,
            3,
            4,
            4,
            3,
            3,
            4,
            3,
            4,
            4,
            3,
            4,
            3,
            24,
            60,
            60,
            24,
            8,
            8,
            8,
            8,
            3,
            1,
            2,
            3,
            2,
            14,
            2,
            14,
            6,
            14,
            0,
            72,
            48,
            56,
            68,
            56,
            84,
            72,
            56,
            68,
            254,
            68,
            72,
            126,
            73,
            1,
            68,
            56,
            40,
            56,
            68,
            3,
            20,
            124,
            20,
            3,
            231,
            231,
            78,
            85,
            85,
            57,
            1,
            1,
            0,
            1,
            1,
            28,
            42,
            85,
            85,
            34,
            28,
            29,
            21,
            30,
            24,
            36,
            0,
            24,
            36,
            8,
            8,
            8,
            24,
            8,
            8,
            8,
            60,
            66,
            189,
            149,
            169,
            66,
            60,
            1,
            1,
            1,
            1,
            1,
            6,
            9,
            9,
            6,
            68,
            68,
            95,
            68,
            68,
            25,
            21,
            18,
            21,
            21,
            10,
            2,
            1,
            252,
            32,
            32,
            28,
            14,
            127,
            1,
            127,
            1,
            24,
            24,
            0,
            128,
            64,
            2,
            31,
            6,
            9,
            9,
            6,
            36,
            24,
            0,
            36,
            24,
            130,
            79,
            48,
            76,
            98,
            241,
            130,
            79,
            48,
            12,
            210,
            177,
            149,
            95,
            48,
            76,
            98,
            241,
            48,
            72,
            69,
            32,
            96,
            57,
            46,
            56,
            96,
            96,
            56,
            46,
            57,
            96,
            112,
            29,
            19,
            29,
            112,
            114,
            29,
            18,
            30,
            113,
            112,
            29,
            18,
            29,
            112,
            96,
            59,
            37,
            59,
            96,
            126,
            17,
            127,
            73,
            65,
            30,
            33,
            97,
            146,
            124,
            85,
            86,
            68,
            124,
            86,
            85,
            68,
            124,
            86,
            85,
            70,
            125,
            84,
            84,
            69,
            69,
            126,
            68,
            68,
            126,
            69,
            70,
            125,
            70,
            69,
            124,
            69,
            8,
            127,
            73,
            65,
            62,
            126,
            9,
            18,
            34,
            125,
            56,
            69,
            70,
            68,
            56,
            56,
            68,
            70,
            69,
            56,
            56,
            70,
            69,
            70,
            56,
            58,
            69,
            69,
            70,
            57,
            56,
            69,
            68,
            69,
            56,
            34,
            20,
            8,
            20,
            34,
            188,
            98,
            90,
            70,
            61,
            60,
            65,
            66,
            60,
            60,
            66,
            65,
            60,
            60,
            66,
            65,
            62,
            61,
            64,
            64,
            61,
            6,
            8,
            242,
            9,
            6,
            127,
            34,
            34,
            28,
            254,
            9,
            137,
            118,
            32,
            85,
            86,
            120,
            32,
            86,
            85,
            120,
            34,
            85,
            85,
            122,
            35,
            85,
            86,
            123,
            32,
            85,
            84,
            121,
            39,
            85,
            87,
            120,
            32,
            84,
            56,
            84,
            72,
            56,
            68,
            196,
            56,
            85,
            86,
            88,
            56,
            86,
            85,
            88,
            58,
            85,
            85,
            90,
            57,
            84,
            84,
            89,
            1,
            122,
            122,
            1,
            2,
            121,
            2,
            2,
            120,
            2,
            96,
            145,
            146,
            124,
            123,
            9,
            10,
            115,
            56,
            69,
            70,
            56,
            56,
            70,
            69,
            56,
            58,
            69,
            69,
            58,
            59,
            69,
            70,
            59,
            57,
            68,
            68,
            57,
            8,
            8,
            42,
            8,
            8,
            184,
            100,
            76,
            58,
            60,
            65,
            66,
            124,
            60,
            66,
            65,
            124,
            58,
            65,
            65,
            122,
            61,
            64,
            64,
            125,
            152,
            98,
            25,
            255,
            66,
            60,
            154,
            96,
            26
        ]
    },
    "_characters": " !\"#$%&'()*+,-./0123456789:;<=>?@ABCDEFGHIJKLMNOPQRSTUVWXYZ[\\]^_`abcdefghijklmnopqrstuvwxyz{|}~€▯‚„…†‡⁀‰˓Œ‘’“”+-˜™˒œ¢£¤¥¦§¨©ª«¬­®¯°±²³´µ¶·¸¹º»¼½¾¿ÀÁÂÃÄÅÆÇÈÉÊËÌÍÎÏÐÑÒÓÔÕÖ×ØÙÚÛÜÝÞßàáâãäåæçèéêëìíîïðñòóôõö÷øùúûüýþÿ"
}